.DS_Store
eta/ApproxClustNum.py
eta/BasicFunc.py
eta/Classifier.py
eta/DefineDevice.py
eta/KeywordDetect.py
eta/OutputPrintFunc.py
eta/PipelineFunc.py
eta/PlotFunc.py
eta/SCCLBert.py
eta/VERSION
eta/__init__.py
eta/__version__.py
eta/cpu.env
eta/cuda.env
eta/dvcGetData.py
eta/main.py
eta/mps.env
eta/py.typed
AnaText-2.1.2.dev0.dist-info/LICENSE.md
AnaText-2.1.2.dev0.dist-info/METADATA
AnaText-2.1.2.dev0.dist-info/WHEEL
AnaText-2.1.2.dev0.dist-info/top_level.txt
AnaText-2.1.2.dev0.dist-info/RECORD
