Metadata-Version: 2.1
Name: AnaText
Version: 2.1.2.dev0
Summary: "The program for solving the problem of exploratory text analysis based on clustering and approximation of the number of clusters."
Author: Roman Neronov
Author-email: roman.nieronov@gmail.com
License: Attribution 4.0 International
Classifier: Development Status :: 1 - Planning
Classifier: Environment :: Console
Classifier: Environment :: GPU :: NVIDIA CUDA
Classifier: Intended Audience :: Science/Research
Classifier: License :: Other/Proprietary License
Classifier: Natural Language :: English
Classifier: Operating System :: OS Independent
Classifier: Programming Language :: Python :: 3.8
Classifier: Programming Language :: Python :: 3.9
Classifier: Programming Language :: Python :: 3.10
Classifier: Programming Language :: Python :: 3.11
Classifier: Programming Language :: Python :: 3.12
Classifier: Topic :: Scientific/Engineering :: Artificial Intelligence
Requires-Python: >=3.8
License-File: LICENSE.md
Requires-Dist: python-dotenv >=0.5.1
Requires-Dist: dvc ==3.36.0
Requires-Dist: keybert ==0.8.3
Requires-Dist: langdetect ==1.0.9
Requires-Dist: matplotlib ==3.8.2
Requires-Dist: numpy ==1.26.1
Requires-Dist: pandas ==2.1.2
Requires-Dist: python-dotenv ==1.0.0
Requires-Dist: scikit-learn ==1.3.2
Requires-Dist: seaborn ==0.13.0
Requires-Dist: sentence-transformers ==2.2.2
Requires-Dist: setuptools ==68.0.0
Requires-Dist: stop-words ==2018.7.23
Requires-Dist: torch ==2.1.0
Requires-Dist: umap-learn ==0.5.4
Requires-Dist: spacy ==3.7.4
